radonpy/__init__.py
radonpy/__main__.py
radonpy/main.py
radonpy-0.2.5.dist-info/licenses/LICENSE.txt
radonpy-0.2.5.dist-info/METADATA
radonpy-0.2.5.dist-info/WHEEL
radonpy-0.2.5.dist-info/entry_points.txt
radonpy-0.2.5.dist-info/top_level.txt
radonpy-0.2.5.dist-info/RECORD
