Metadata-Version: 2.4
Name: radonpy
Version: 0.2.5
Summary: Tools to communicate with the RadonEye RD200 radon detector
Author-email: Ben Wolsieffer <benwolsieffer@gmail.com>
License-Expression: Apache-2.0
Project-URL: Repository, https://github.com/lopsided98/radonpy.git
Project-URL: Issues, https://github.com/lopsided98/radonpy/issues
Keywords: radon,radoneye
Classifier: Development Status :: 4 - Beta
Classifier: Topic :: Home Automation
License-File: LICENSE.txt
Requires-Dist: aioinflux
Requires-Dist: bleak>=1.0.0
Dynamic: license-file
